#pragma once
#include "../defines.h"

const u8 ACONST_NULL = 1;
const u8 ICONST_0 = 3;
const u8 ICONST_1 = 4;
const u8 LDC = 18;
const u8 ILOAD_1 = 27;
const u8 ALOAD_0 = 42;
const u8 ASTORE_1 = 76;
const u8 DUP = 89;
const u8 IFEQ = 153;
const u8 IFNE = 154;
const u8 GOTO = 167;
const u8 IRETURN = 172;
const u8 RETURN = 177;
const u8 GETSTATIC = 178;
const u8 PUTSTATIC = 179;
const u8 GETFIELD = 180;
const u8 PUTFIELD = 181;
const u8 INVOKEVIRTUAL = 182;
const u8 INVOKESPECIAL = 183;
const u8 NEW = 187;
const u8 ATHROW = 191;
const u8 CHECKCAST = 192;